{"nodes": [{"id": "c_users_dell_documents_github_personal_working_days_apps_api_src_modules_employees_employees_service_ts", "label": "employees.service.ts", "file_type": "code", "source_file": "C:\\Users\\Dell\\Documents\\GitHub\\Personal\\working-days\\apps\\api\\src\\modules\\employees\\employees.service.ts", "source_location": "L1"}, {"id": "employees_employees_service_employeesservice", "label": "EmployeesService", "file_type": "code", "source_file": "C:\\Users\\Dell\\Documents\\GitHub\\Personal\\working-days\\apps\\api\\src\\modules\\employees\\employees.service.ts", "source_location": "L13"}, {"id": "employees_employees_service_employeesservice_constructor", "label": ".constructor()", "file_type": "code", "source_file": "C:\\Users\\Dell\\Documents\\GitHub\\Personal\\working-days\\apps\\api\\src\\modules\\employees\\employees.service.ts", "source_location": "L16"}, {"id": "employees_employees_service_employeesservice_findall", "label": ".findAll()", "file_type": "code", "source_file": "C:\\Users\\Dell\\Documents\\GitHub\\Personal\\working-days\\apps\\api\\src\\modules\\employees\\employees.service.ts", "source_location": "L21"}, {"id": "employees_employees_service_employeesservice_findbyid", "label": ".findById()", "file_type": "code", "source_file": "C:\\Users\\Dell\\Documents\\GitHub\\Personal\\working-days\\apps\\api\\src\\modules\\employees\\employees.service.ts", "source_location": "L78"}, {"id": "employees_employees_service_employeesservice_create", "label": ".create()", "file_type": "code", "source_file": "C:\\Users\\Dell\\Documents\\GitHub\\Personal\\working-days\\apps\\api\\src\\modules\\employees\\employees.service.ts", "source_location": "L113"}, {"id": "employees_employees_service_employeesservice_update", "label": ".update()", "file_type": "code", "source_file": "C:\\Users\\Dell\\Documents\\GitHub\\Personal\\working-days\\apps\\api\\src\\modules\\employees\\employees.service.ts", "source_location": "L138"}, {"id": "employees_employees_service_employeesservice_createemployeeasadmin", "label": ".createEmployeeAsAdmin()", "file_type": "code", "source_file": "C:\\Users\\Dell\\Documents\\GitHub\\Personal\\working-days\\apps\\api\\src\\modules\\employees\\employees.service.ts", "source_location": "L163"}, {"id": "employees_employees_service_employeesservice_updateemployeeasadmin", "label": ".updateEmployeeAsAdmin()", "file_type": "code", "source_file": "C:\\Users\\Dell\\Documents\\GitHub\\Personal\\working-days\\apps\\api\\src\\modules\\employees\\employees.service.ts", "source_location": "L232"}, {"id": "employees_employees_service_employeesservice_changestatus", "label": ".changeStatus()", "file_type": "code", "source_file": "C:\\Users\\Dell\\Documents\\GitHub\\Personal\\working-days\\apps\\api\\src\\modules\\employees\\employees.service.ts", "source_location": "L292"}, {"id": "employees_employees_service_employeesservice_resetpasswordasadmin", "label": ".resetPasswordAsAdmin()", "file_type": "code", "source_file": "C:\\Users\\Dell\\Documents\\GitHub\\Personal\\working-days\\apps\\api\\src\\modules\\employees\\employees.service.ts", "source_location": "L309"}, {"id": "employees_employees_service_employeesservice_changerole", "label": ".changeRole()", "file_type": "code", "source_file": "C:\\Users\\Dell\\Documents\\GitHub\\Personal\\working-days\\apps\\api\\src\\modules\\employees\\employees.service.ts", "source_location": "L332"}], "edges": [{"source": "c_users_dell_documents_github_personal_working_days_apps_api_src_modules_employees_employees_service_ts", "target": "common", "relation": "imports_from", "context": "import", "confidence": "EXTRACTED", "source_file": "C:\\Users\\Dell\\Documents\\GitHub\\Personal\\working-days\\apps\\api\\src\\modules\\employees\\employees.service.ts", "source_location": "L1", "weight": 1.0}, {"source": "c_users_dell_documents_github_personal_working_days_apps_api_src_modules_employees_employees_service_ts", "target": "event_emitter", "relation": "imports_from", "context": "import", "confidence": "EXTRACTED", "source_file": "C:\\Users\\Dell\\Documents\\GitHub\\Personal\\working-days\\apps\\api\\src\\modules\\employees\\employees.service.ts", "source_location": "L2", "weight": 1.0}, {"source": "c_users_dell_documents_github_personal_working_days_apps_api_src_modules_employees_employees_service_ts", "target": "bcrypt", "relation": "imports_from", "context": "import", "confidence": "EXTRACTED", "source_file": "C:\\Users\\Dell\\Documents\\GitHub\\Personal\\working-days\\apps\\api\\src\\modules\\employees\\employees.service.ts", "source_location": "L3", "weight": 1.0}, {"source": "c_users_dell_documents_github_personal_working_days_apps_api_src_modules_employees_employees_service_ts", "target": "c_users_dell_documents_github_personal_working_days_apps_api_src_database_prisma_service_ts", "relation": "imports_from", "context": "import", "confidence": "EXTRACTED", "source_file": "C:\\Users\\Dell\\Documents\\GitHub\\Personal\\working-days\\apps\\api\\src\\modules\\employees\\employees.service.ts", "source_location": "L5", "weight": 1.0}, {"source": "c_users_dell_documents_github_personal_working_days_apps_api_src_modules_employees_employees_service_ts", "target": "database_prisma_service_prismaservice", "relation": "imports", "context": "import", "confidence": "EXTRACTED", "source_file": "C:\\Users\\Dell\\Documents\\GitHub\\Personal\\working-days\\apps\\api\\src\\modules\\employees\\employees.service.ts", "source_location": "L5", "weight": 1.0}, {"source": "c_users_dell_documents_github_personal_working_days_apps_api_src_modules_employees_employees_service_ts", "target": "c_users_dell_documents_github_personal_working_days_apps_api_src_common_dto_pagination_dto_ts", "relation": "imports_from", "context": "import", "confidence": "EXTRACTED", "source_file": "C:\\Users\\Dell\\Documents\\GitHub\\Personal\\working-days\\apps\\api\\src\\modules\\employees\\employees.service.ts", "source_location": "L6", "weight": 1.0}, {"source": "c_users_dell_documents_github_personal_working_days_apps_api_src_modules_employees_employees_service_ts", "target": "dto_pagination_dto_paginationdto", "relation": "imports", "context": "import", "confidence": "EXTRACTED", "source_file": "C:\\Users\\Dell\\Documents\\GitHub\\Personal\\working-days\\apps\\api\\src\\modules\\employees\\employees.service.ts", "source_location": "L6", "weight": 1.0}, {"source": "c_users_dell_documents_github_personal_working_days_apps_api_src_modules_employees_employees_service_ts", "target": "c_users_dell_documents_github_personal_working_days_apps_api_src_modules_employees_dto_create_employee_dto_ts", "relation": "imports_from", "context": "import", "confidence": "EXTRACTED", "source_file": "C:\\Users\\Dell\\Documents\\GitHub\\Personal\\working-days\\apps\\api\\src\\modules\\employees\\employees.service.ts", "source_location": "L7", "weight": 1.0}, {"source": "c_users_dell_documents_github_personal_working_days_apps_api_src_modules_employees_employees_service_ts", "target": "dto_create_employee_dto_createemployeedto", "relation": "imports", "context": "import", "confidence": "EXTRACTED", "source_file": "C:\\Users\\Dell\\Documents\\GitHub\\Personal\\working-days\\apps\\api\\src\\modules\\employees\\employees.service.ts", "source_location": "L7", "weight": 1.0}, {"source": "c_users_dell_documents_github_personal_working_days_apps_api_src_modules_employees_employees_service_ts", "target": "c_users_dell_documents_github_personal_working_days_apps_api_src_modules_employees_dto_update_employee_dto_ts", "relation": "imports_from", "context": "import", "confidence": "EXTRACTED", "source_file": "C:\\Users\\Dell\\Documents\\GitHub\\Personal\\working-days\\apps\\api\\src\\modules\\employees\\employees.service.ts", "source_location": "L8", "weight": 1.0}, {"source": "c_users_dell_documents_github_personal_working_days_apps_api_src_modules_employees_employees_service_ts", "target": "dto_update_employee_dto_updateemployeedto", "relation": "imports", "context": "import", "confidence": "EXTRACTED", "source_file": "C:\\Users\\Dell\\Documents\\GitHub\\Personal\\working-days\\apps\\api\\src\\modules\\employees\\employees.service.ts", "source_location": "L8", "weight": 1.0}, {"source": "c_users_dell_documents_github_personal_working_days_apps_api_src_modules_employees_employees_service_ts", "target": "c_users_dell_documents_github_personal_working_days_apps_api_src_modules_employees_dto_admin_employee_dto_ts", "relation": "imports_from", "context": "import", "confidence": "EXTRACTED", "source_file": "C:\\Users\\Dell\\Documents\\GitHub\\Personal\\working-days\\apps\\api\\src\\modules\\employees\\employees.service.ts", "source_location": "L9", "weight": 1.0}, {"source": "c_users_dell_documents_github_personal_working_days_apps_api_src_modules_employees_employees_service_ts", "target": "dto_admin_employee_dto_admincreateemployeedto", "relation": "imports", "context": "import", "confidence": "EXTRACTED", "source_file": "C:\\Users\\Dell\\Documents\\GitHub\\Personal\\working-days\\apps\\api\\src\\modules\\employees\\employees.service.ts", "source_location": "L9", "weight": 1.0}, {"source": "c_users_dell_documents_github_personal_working_days_apps_api_src_modules_employees_employees_service_ts", "target": "dto_admin_employee_dto_adminupdateemployeedto", "relation": "imports", "context": "import", "confidence": "EXTRACTED", "source_file": "C:\\Users\\Dell\\Documents\\GitHub\\Personal\\working-days\\apps\\api\\src\\modules\\employees\\employees.service.ts", "source_location": "L9", "weight": 1.0}, {"source": "c_users_dell_documents_github_personal_working_days_apps_api_src_modules_employees_employees_service_ts", "target": "dto_admin_employee_dto_changeroledto", "relation": "imports", "context": "import", "confidence": "EXTRACTED", "source_file": "C:\\Users\\Dell\\Documents\\GitHub\\Personal\\working-days\\apps\\api\\src\\modules\\employees\\employees.service.ts", "source_location": "L9", "weight": 1.0}, {"source": "c_users_dell_documents_github_personal_working_days_apps_api_src_modules_employees_employees_service_ts", "target": "dto_admin_employee_dto_resetpassworddto", "relation": "imports", "context": "import", "confidence": "EXTRACTED", "source_file": "C:\\Users\\Dell\\Documents\\GitHub\\Personal\\working-days\\apps\\api\\src\\modules\\employees\\employees.service.ts", "source_location": "L9", "weight": 1.0}, {"source": "c_users_dell_documents_github_personal_working_days_apps_api_src_modules_employees_employees_service_ts", "target": "dto_admin_employee_dto_changestatusdto", "relation": "imports", "context": "import", "confidence": "EXTRACTED", "source_file": "C:\\Users\\Dell\\Documents\\GitHub\\Personal\\working-days\\apps\\api\\src\\modules\\employees\\employees.service.ts", "source_location": "L9", "weight": 1.0}, {"source": "c_users_dell_documents_github_personal_working_days_apps_api_src_modules_employees_employees_service_ts", "target": "c_users_dell_documents_github_personal_working_days_apps_api_src_common_constants_index_ts", "relation": "imports_from", "context": "import", "confidence": "EXTRACTED", "source_file": "C:\\Users\\Dell\\Documents\\GitHub\\Personal\\working-days\\apps\\api\\src\\modules\\employees\\employees.service.ts", "source_location": "L10", "weight": 1.0}, {"source": "c_users_dell_documents_github_personal_working_days_apps_api_src_modules_employees_employees_service_ts", "target": "constants_index_app_constants", "relation": "imports", "context": "import", "confidence": "EXTRACTED", "source_file": "C:\\Users\\Dell\\Documents\\GitHub\\Personal\\working-days\\apps\\api\\src\\modules\\employees\\employees.service.ts", "source_location": "L10", "weight": 1.0}, {"source": "c_users_dell_documents_github_personal_working_days_apps_api_src_modules_employees_employees_service_ts", "target": "employees_employees_service_employeesservice", "relation": "contains", "confidence": "EXTRACTED", "source_file": "C:\\Users\\Dell\\Documents\\GitHub\\Personal\\working-days\\apps\\api\\src\\modules\\employees\\employees.service.ts", "source_location": "L13", "weight": 1.0}, {"source": "employees_employees_service_employeesservice", "target": "employees_employees_service_employeesservice_constructor", "relation": "method", "confidence": "EXTRACTED", "source_file": "C:\\Users\\Dell\\Documents\\GitHub\\Personal\\working-days\\apps\\api\\src\\modules\\employees\\employees.service.ts", "source_location": "L16", "weight": 1.0}, {"source": "employees_employees_service_employeesservice", "target": "employees_employees_service_employeesservice_findall", "relation": "method", "confidence": "EXTRACTED", "source_file": "C:\\Users\\Dell\\Documents\\GitHub\\Personal\\working-days\\apps\\api\\src\\modules\\employees\\employees.service.ts", "source_location": "L21", "weight": 1.0}, {"source": "employees_employees_service_employeesservice", "target": "employees_employees_service_employeesservice_findbyid", "relation": "method", "confidence": "EXTRACTED", "source_file": "C:\\Users\\Dell\\Documents\\GitHub\\Personal\\working-days\\apps\\api\\src\\modules\\employees\\employees.service.ts", "source_location": "L78", "weight": 1.0}, {"source": "employees_employees_service_employeesservice", "target": "employees_employees_service_employeesservice_create", "relation": "method", "confidence": "EXTRACTED", "source_file": "C:\\Users\\Dell\\Documents\\GitHub\\Personal\\working-days\\apps\\api\\src\\modules\\employees\\employees.service.ts", "source_location": "L113", "weight": 1.0}, {"source": "employees_employees_service_employeesservice", "target": "employees_employees_service_employeesservice_update", "relation": "method", "confidence": "EXTRACTED", "source_file": "C:\\Users\\Dell\\Documents\\GitHub\\Personal\\working-days\\apps\\api\\src\\modules\\employees\\employees.service.ts", "source_location": "L138", "weight": 1.0}, {"source": "employees_employees_service_employeesservice", "target": "employees_employees_service_employeesservice_createemployeeasadmin", "relation": "method", "confidence": "EXTRACTED", "source_file": "C:\\Users\\Dell\\Documents\\GitHub\\Personal\\working-days\\apps\\api\\src\\modules\\employees\\employees.service.ts", "source_location": "L163", "weight": 1.0}, {"source": "employees_employees_service_employeesservice", "target": "employees_employees_service_employeesservice_updateemployeeasadmin", "relation": "method", "confidence": "EXTRACTED", "source_file": "C:\\Users\\Dell\\Documents\\GitHub\\Personal\\working-days\\apps\\api\\src\\modules\\employees\\employees.service.ts", "source_location": "L232", "weight": 1.0}, {"source": "employees_employees_service_employeesservice", "target": "employees_employees_service_employeesservice_changestatus", "relation": "method", "confidence": "EXTRACTED", "source_file": "C:\\Users\\Dell\\Documents\\GitHub\\Personal\\working-days\\apps\\api\\src\\modules\\employees\\employees.service.ts", "source_location": "L292", "weight": 1.0}, {"source": "employees_employees_service_employeesservice", "target": "employees_employees_service_employeesservice_resetpasswordasadmin", "relation": "method", "confidence": "EXTRACTED", "source_file": "C:\\Users\\Dell\\Documents\\GitHub\\Personal\\working-days\\apps\\api\\src\\modules\\employees\\employees.service.ts", "source_location": "L309", "weight": 1.0}, {"source": "employees_employees_service_employeesservice", "target": "employees_employees_service_employeesservice_changerole", "relation": "method", "confidence": "EXTRACTED", "source_file": "C:\\Users\\Dell\\Documents\\GitHub\\Personal\\working-days\\apps\\api\\src\\modules\\employees\\employees.service.ts", "source_location": "L332", "weight": 1.0}, {"source": "employees_employees_service_employeesservice_createemployeeasadmin", "target": "employees_employees_service_employeesservice_create", "relation": "calls", "context": "call", "confidence": "EXTRACTED", "source_file": "C:\\Users\\Dell\\Documents\\GitHub\\Personal\\working-days\\apps\\api\\src\\modules\\employees\\employees.service.ts", "source_location": "L179", "weight": 1.0}, {"source": "employees_employees_service_employeesservice_updateemployeeasadmin", "target": "employees_employees_service_employeesservice_findbyid", "relation": "calls", "context": "call", "confidence": "EXTRACTED", "source_file": "C:\\Users\\Dell\\Documents\\GitHub\\Personal\\working-days\\apps\\api\\src\\modules\\employees\\employees.service.ts", "source_location": "L233", "weight": 1.0}, {"source": "employees_employees_service_employeesservice_updateemployeeasadmin", "target": "employees_employees_service_employeesservice_update", "relation": "calls", "context": "call", "confidence": "EXTRACTED", "source_file": "C:\\Users\\Dell\\Documents\\GitHub\\Personal\\working-days\\apps\\api\\src\\modules\\employees\\employees.service.ts", "source_location": "L246", "weight": 1.0}, {"source": "employees_employees_service_employeesservice_updateemployeeasadmin", "target": "employees_employees_service_employeesservice_changerole", "relation": "calls", "context": "call", "confidence": "EXTRACTED", "source_file": "C:\\Users\\Dell\\Documents\\GitHub\\Personal\\working-days\\apps\\api\\src\\modules\\employees\\employees.service.ts", "source_location": "L284", "weight": 1.0}, {"source": "employees_employees_service_employeesservice_changestatus", "target": "employees_employees_service_employeesservice_findbyid", "relation": "calls", "context": "call", "confidence": "EXTRACTED", "source_file": "C:\\Users\\Dell\\Documents\\GitHub\\Personal\\working-days\\apps\\api\\src\\modules\\employees\\employees.service.ts", "source_location": "L293", "weight": 1.0}, {"source": "employees_employees_service_employeesservice_changestatus", "target": "employees_employees_service_employeesservice_update", "relation": "calls", "context": "call", "confidence": "EXTRACTED", "source_file": "C:\\Users\\Dell\\Documents\\GitHub\\Personal\\working-days\\apps\\api\\src\\modules\\employees\\employees.service.ts", "source_location": "L294", "weight": 1.0}, {"source": "employees_employees_service_employeesservice_resetpasswordasadmin", "target": "employees_employees_service_employeesservice_findbyid", "relation": "calls", "context": "call", "confidence": "EXTRACTED", "source_file": "C:\\Users\\Dell\\Documents\\GitHub\\Personal\\working-days\\apps\\api\\src\\modules\\employees\\employees.service.ts", "source_location": "L310", "weight": 1.0}, {"source": "employees_employees_service_employeesservice_resetpasswordasadmin", "target": "employees_employees_service_employeesservice_update", "relation": "calls", "context": "call", "confidence": "EXTRACTED", "source_file": "C:\\Users\\Dell\\Documents\\GitHub\\Personal\\working-days\\apps\\api\\src\\modules\\employees\\employees.service.ts", "source_location": "L314", "weight": 1.0}, {"source": "employees_employees_service_employeesservice_changerole", "target": "employees_employees_service_employeesservice_findbyid", "relation": "calls", "context": "call", "confidence": "EXTRACTED", "source_file": "C:\\Users\\Dell\\Documents\\GitHub\\Personal\\working-days\\apps\\api\\src\\modules\\employees\\employees.service.ts", "source_location": "L333", "weight": 1.0}, {"source": "employees_employees_service_employeesservice_changerole", "target": "employees_employees_service_employeesservice_update", "relation": "calls", "context": "call", "confidence": "EXTRACTED", "source_file": "C:\\Users\\Dell\\Documents\\GitHub\\Personal\\working-days\\apps\\api\\src\\modules\\employees\\employees.service.ts", "source_location": "L341", "weight": 1.0}], "raw_calls": [{"caller_nid": "employees_employees_service_employeesservice_findall", "callee": "all", "is_member_call": true, "source_file": "C:\\Users\\Dell\\Documents\\GitHub\\Personal\\working-days\\apps\\api\\src\\modules\\employees\\employees.service.ts", "source_location": "L35"}, {"caller_nid": "employees_employees_service_employeesservice_findall", "callee": "findMany", "is_member_call": true, "source_file": "C:\\Users\\Dell\\Documents\\GitHub\\Personal\\working-days\\apps\\api\\src\\modules\\employees\\employees.service.ts", "source_location": "L36"}, {"caller_nid": "employees_employees_service_employeesservice_findall", "callee": "count", "is_member_call": true, "source_file": "C:\\Users\\Dell\\Documents\\GitHub\\Personal\\working-days\\apps\\api\\src\\modules\\employees\\employees.service.ts", "source_location": "L62"}, {"caller_nid": "employees_employees_service_employeesservice_findall", "callee": "ceil", "is_member_call": true, "source_file": "C:\\Users\\Dell\\Documents\\GitHub\\Personal\\working-days\\apps\\api\\src\\modules\\employees\\employees.service.ts", "source_location": "L71"}, {"caller_nid": "employees_employees_service_employeesservice_findbyid", "callee": "findUnique", "is_member_call": true, "source_file": "C:\\Users\\Dell\\Documents\\GitHub\\Personal\\working-days\\apps\\api\\src\\modules\\employees\\employees.service.ts", "source_location": "L79"}, {"caller_nid": "employees_employees_service_employeesservice_create", "callee": "emit", "is_member_call": true, "source_file": "C:\\Users\\Dell\\Documents\\GitHub\\Personal\\working-days\\apps\\api\\src\\modules\\employees\\employees.service.ts", "source_location": "L134"}, {"caller_nid": "employees_employees_service_employeesservice_update", "callee": "findUnique", "is_member_call": true, "source_file": "C:\\Users\\Dell\\Documents\\GitHub\\Personal\\working-days\\apps\\api\\src\\modules\\employees\\employees.service.ts", "source_location": "L139"}, {"caller_nid": "employees_employees_service_employeesservice_update", "callee": "emit", "is_member_call": true, "source_file": "C:\\Users\\Dell\\Documents\\GitHub\\Personal\\working-days\\apps\\api\\src\\modules\\employees\\employees.service.ts", "source_location": "L159"}, {"caller_nid": "employees_employees_service_employeesservice_createemployeeasadmin", "callee": "findUnique", "is_member_call": true, "source_file": "C:\\Users\\Dell\\Documents\\GitHub\\Personal\\working-days\\apps\\api\\src\\modules\\employees\\employees.service.ts", "source_location": "L164"}, {"caller_nid": "employees_employees_service_employeesservice_createemployeeasadmin", "callee": "slice", "is_member_call": true, "source_file": "C:\\Users\\Dell\\Documents\\GitHub\\Personal\\working-days\\apps\\api\\src\\modules\\employees\\employees.service.ts", "source_location": "L173"}, {"caller_nid": "employees_employees_service_employeesservice_createemployeeasadmin", "callee": "toString", "is_member_call": true, "source_file": "C:\\Users\\Dell\\Documents\\GitHub\\Personal\\working-days\\apps\\api\\src\\modules\\employees\\employees.service.ts", "source_location": "L173"}, {"caller_nid": "employees_employees_service_employeesservice_createemployeeasadmin", "callee": "random", "is_member_call": true, "source_file": "C:\\Users\\Dell\\Documents\\GitHub\\Personal\\working-days\\apps\\api\\src\\modules\\employees\\employees.service.ts", "source_location": "L173"}, {"caller_nid": "employees_employees_service_employeesservice_createemployeeasadmin", "callee": "hash", "is_member_call": true, "source_file": "C:\\Users\\Dell\\Documents\\GitHub\\Personal\\working-days\\apps\\api\\src\\modules\\employees\\employees.service.ts", "source_location": "L174"}, {"caller_nid": "employees_employees_service_employeesservice_createemployeeasadmin", "callee": "slice", "is_member_call": true, "source_file": "C:\\Users\\Dell\\Documents\\GitHub\\Personal\\working-days\\apps\\api\\src\\modules\\employees\\employees.service.ts", "source_location": "L177"}, {"caller_nid": "employees_employees_service_employeesservice_createemployeeasadmin", "callee": "toString", "is_member_call": true, "source_file": "C:\\Users\\Dell\\Documents\\GitHub\\Personal\\working-days\\apps\\api\\src\\modules\\employees\\employees.service.ts", "source_location": "L177"}, {"caller_nid": "employees_employees_service_employeesservice_createemployeeasadmin", "callee": "now", "is_member_call": true, "source_file": "C:\\Users\\Dell\\Documents\\GitHub\\Personal\\working-days\\apps\\api\\src\\modules\\employees\\employees.service.ts", "source_location": "L177"}, {"caller_nid": "employees_employees_service_employeesservice_createemployeeasadmin", "callee": "map", "is_member_call": true, "source_file": "C:\\Users\\Dell\\Documents\\GitHub\\Personal\\working-days\\apps\\api\\src\\modules\\employees\\employees.service.ts", "source_location": "L204"}, {"caller_nid": "employees_employees_service_employeesservice_createemployeeasadmin", "callee": "log", "is_member_call": true, "source_file": "C:\\Users\\Dell\\Documents\\GitHub\\Personal\\working-days\\apps\\api\\src\\modules\\employees\\employees.service.ts", "source_location": "L222"}, {"caller_nid": "employees_employees_service_employeesservice_createemployeeasadmin", "callee": "map", "is_member_call": true, "source_file": "C:\\Users\\Dell\\Documents\\GitHub\\Personal\\working-days\\apps\\api\\src\\modules\\employees\\employees.service.ts", "source_location": "L227"}, {"caller_nid": "employees_employees_service_employeesservice_updateemployeeasadmin", "callee": "findUnique", "is_member_call": true, "source_file": "C:\\Users\\Dell\\Documents\\GitHub\\Personal\\working-days\\apps\\api\\src\\modules\\employees\\employees.service.ts", "source_location": "L238"}, {"caller_nid": "employees_employees_service_employeesservice_updateemployeeasadmin", "callee": "log", "is_member_call": true, "source_file": "C:\\Users\\Dell\\Documents\\GitHub\\Personal\\working-days\\apps\\api\\src\\modules\\employees\\employees.service.ts", "source_location": "L287"}, {"caller_nid": "employees_employees_service_employeesservice_resetpasswordasadmin", "callee": "slice", "is_member_call": true, "source_file": "C:\\Users\\Dell\\Documents\\GitHub\\Personal\\working-days\\apps\\api\\src\\modules\\employees\\employees.service.ts", "source_location": "L311"}, {"caller_nid": "employees_employees_service_employeesservice_resetpasswordasadmin", "callee": "toString", "is_member_call": true, "source_file": "C:\\Users\\Dell\\Documents\\GitHub\\Personal\\working-days\\apps\\api\\src\\modules\\employees\\employees.service.ts", "source_location": "L311"}, {"caller_nid": "employees_employees_service_employeesservice_resetpasswordasadmin", "callee": "random", "is_member_call": true, "source_file": "C:\\Users\\Dell\\Documents\\GitHub\\Personal\\working-days\\apps\\api\\src\\modules\\employees\\employees.service.ts", "source_location": "L311"}, {"caller_nid": "employees_employees_service_employeesservice_resetpasswordasadmin", "callee": "hash", "is_member_call": true, "source_file": "C:\\Users\\Dell\\Documents\\GitHub\\Personal\\working-days\\apps\\api\\src\\modules\\employees\\employees.service.ts", "source_location": "L312"}, {"caller_nid": "employees_employees_service_employeesservice_resetpasswordasadmin", "callee": "deleteMany", "is_member_call": true, "source_file": "C:\\Users\\Dell\\Documents\\GitHub\\Personal\\working-days\\apps\\api\\src\\modules\\employees\\employees.service.ts", "source_location": "L323"}, {"caller_nid": "employees_employees_service_employeesservice_resetpasswordasadmin", "callee": "log", "is_member_call": true, "source_file": "C:\\Users\\Dell\\Documents\\GitHub\\Personal\\working-days\\apps\\api\\src\\modules\\employees\\employees.service.ts", "source_location": "L327"}, {"caller_nid": "employees_employees_service_employeesservice_changerole", "callee": "deleteMany", "is_member_call": true, "source_file": "C:\\Users\\Dell\\Documents\\GitHub\\Personal\\working-days\\apps\\api\\src\\modules\\employees\\employees.service.ts", "source_location": "L336"}, {"caller_nid": "employees_employees_service_employeesservice_changerole", "callee": "map", "is_member_call": true, "source_file": "C:\\Users\\Dell\\Documents\\GitHub\\Personal\\working-days\\apps\\api\\src\\modules\\employees\\employees.service.ts", "source_location": "L345"}, {"caller_nid": "employees_employees_service_employeesservice_changerole", "callee": "map", "is_member_call": true, "source_file": "C:\\Users\\Dell\\Documents\\GitHub\\Personal\\working-days\\apps\\api\\src\\modules\\employees\\employees.service.ts", "source_location": "L360"}]}